PyPDPM/HIPPS.py
PyPDPM/__init__.py
PyPDPM/data/PDPM_ICD10_Mappings_FY2020_NTA.json
PyPDPM/data/PDPM_ICD10_Mappings_FY2020_SLP.json
PyPDPM/data/PDPM_ICD10_Mappings_FY2020_clinical_category.json
PyPDPM-0.0.5.20.dist-info/LICENSE.txt
PyPDPM-0.0.5.20.dist-info/METADATA
PyPDPM-0.0.5.20.dist-info/WHEEL
PyPDPM-0.0.5.20.dist-info/top_level.txt
PyPDPM-0.0.5.20.dist-info/RECORD
