Metadata-Version: 2.1
Name: PyPDPM
Version: 0.0.5.20
Summary: A Python library for dealing with PDPM HIPP codes
Home-page: https://github.com/Scorks/PyPDPM
Author: Caro Strickland
Author-email: carostrickland321@gmail.com
License: MIT
Keywords: PDPM,HIPPS,ICD-10-CM Codes
License-File: LICENSE.txt
